Metadata-Version: 2.1
Name: neon-stt-plugin-google-cloud-streaming
Version: 2.0.0
Summary: A Google streaming stt plugin for Neon
Home-page: https://github.com/NeonGeckoCom/neon-stt-plugin-google_cloud_streaming
Author: Neongecko
Author-email: developers@neon.ai
License: BSD-3
Keywords: mycroft plugin stt
Classifier: Intended Audience :: Developers
Classifier: Topic :: Text Processing :: Linguistic
Classifier: Programming Language :: Python :: 3.6
License-File: LICENSE.md
Requires-Dist: google-cloud-speech~=2.4
Requires-Dist: google-api-python-client~=1.6
Requires-Dist: SpeechRecognition~=3.8
Requires-Dist: ovos-plugin-manager~=0.0
Requires-Dist: ovos-utils~=0.0
Requires-Dist: google-api-core~=2.11
